a_pandas_ex_to_tuple/LICENSE
a_pandas_ex_to_tuple/README.MD
a_pandas_ex_to_tuple/__init__.py
a_pandas_ex_to_tuple/requirements.txt
a_pandas_ex_to_tuple/thirdparty.json
a_pandas_ex_to_tuple-0.10.dist-info/LICENSE.rst
a_pandas_ex_to_tuple-0.10.dist-info/METADATA
a_pandas_ex_to_tuple-0.10.dist-info/WHEEL
a_pandas_ex_to_tuple-0.10.dist-info/top_level.txt
a_pandas_ex_to_tuple-0.10.dist-info/RECORD
